LAB08/Ejercicio 3 lab8/Ejercicio3.v
module ALU(input wire [3:0]A, input wire [3:0]B, input wire [2:0]COM, output reg [3:0]R);


    always @ (A or B or COM)begin
// El case es como una pantalla de seleccion de comando
      case(COM)
          3'b000: R = A & B;// comando para and
          3'b001: R = A | B;// comando para or
          3'b010: R = A + B;// suma
          3'b100: R = A & ~B;// Comando para a and not b
          3'b101: R = A | ~B;// comando para a or not b
          3'b110: R = A - B;// resta
          3'b111: R = (A < B) ? 1:0;// comparacion
          default: R = 3'b000;// si no se le asigna valor queda en la primera
      endcase
    end
endmodule

LAB08/Ejercicio 3 lab8/Ejercicio3_tb.v
module testbench();

reg [3:0]A;
reg [3:0]B;
reg [2:0]COM;
wire [3:0]R;

ALU calc(A, B, COM, R);


initial begin
  #2
  $display("   A   |    B    |    COM    |   R    ");
  $display("--------------------------------------");
  $monitor("   %b       %b        %b         %b", A, B, COM, R);
      A = 4'b0000; B = 4'b0000; COM = 3'b000;
  #1 A = 4'b0001; B = 4'b0111; COM = 3'b000;
  #1 A = 4'b0010; B = 4'b0101; COM = 3'b001;
  #1 A = 4'b0011; B = 4'b0100; COM = 3'b010;
  #1 A = 4'b0100; B = 4'b0001; COM = 3'b100;
  #1 A = 4'b0101; B = 4'b0011; COM = 3'b101;
  #1 A = 4'b0110; B = 4'b0010; COM = 3'b110;
  #1 A = 4'b0111; B = 4'b0001; COM = 3'b111;

end
initial
#20 $finish;

initial begin
  $dumpfile("Ejercicio3_tb.vcd");
  $dumpvars(0, testbench);
end
endmodule

LAB08/Ejercicio 3 lab8/Ejercicio3_tb.vcd
$date
	Sat Oct 24 19:12:41 2020
$end
$version
	Icarus Verilog
$end
$timescale
	1ps
$end
$scope module testbench $end
$var wire 4 ! R [3:0] $end
$var reg 4 " A [3:0] $end
$var reg 4 # B [3:0] $end
$var reg 3 $ COM [2:0] $end
$scope module calc $end
$var wire 4 % A [3:0] $end
$var wire 4 & B [3:0] $end
$var wire 3 ' COM [2:0] $end
$var reg 4 ( R [3:0] $end
$upscope $end
$upscope $end
$enddefinitions $end
#0
$dumpvars
bx (
bx '
bx &
bx %
bx $
bx #
bx "
bx !
$end
#2
b0 !
b0 (
b0 $
b0 '
b0 #
b0 &
b0 "
b0 %
#3
b1 !
b1 (
b111 #
b111 &
b1 "
b1 %
#4
b111 !
b111 (
b1 $
b1 '
b101 #
b101 &
b10 "
b10 %
#5
b10 $
b10 '
b100 #
b100 &
b11 "
b11 %
#6
b100 !
b100 (
b100 $
b100 '
b1 #
b1 &
b100 "
b100 %
#7
b1101 !
b1101 (
b101 $
b101 '
b11 #
b11 &
b101 "
b101 %
#8
b100 !
b100 (
b110 $
b110 '
b10 #
b10 &
b110 "
b110 %
#9
b0 !
b0 (
b111 $
b111 '
b1 #
b1 &
b111 "
b111 %
