LAB09/Ejercicio5 lab9 /Ejercicio 5.v
module ROM_5(input wire [6:0]I, output reg [12:0]O);
reg [12:0] ROM [0:127];
  always @ (I)begin

    casez(I)
        7'b??????0: O = 13'b1000000001000;//
        7'b00001?1: O = 13'b0100000001000;//
        7'b00000?1: O = 13'b1000000001000;//
        7'b00011?1: O = 13'b1000000001000;//
        7'b00010?1: O = 13'b0100000001000;//
        7'b0010??1: O = 13'b0001001000010;//
        7'b0011??1: O = 13'b1001001100000;//
        7'b0100??1: O = 13'b0011010000010;//
        7'b0101??1: O = 13'b0011010000100;//
        7'b0110??1: O = 13'b1011010100000;//
        7'b0111??1: O = 13'b1000000111000;//
        7'b1000?11: O = 13'b0100000001000;//
        7'b1000?01: O = 13'b1000000001000;//
        7'b1001?11: O = 13'b1000000001000;//
        7'b1001?01: O = 13'b0100000001000;//
        7'b1010??1: O = 13'b0011011000010;//
        7'b1011??1: O = 13'b1011011100000;//
        7'b1100??1: O = 13'b0100000001000;//
        7'b1101??1: O = 13'b0000000001001;//
        7'b1110??1: O = 13'b0011100000010;//
        7'b1111??1: O = 13'b1011100100000;//
        default: O = 7'b??????0;// si no se le asigna valor queda en la primera
    endcase
  end
endmodule

LAB09/Ejercicio5 lab9 /Ejercicio5_tb.v
module testbench();

reg [6:0]I;
wire [12:0]O;

ROM_5 MROM(I, O);

initial begin
#1
$display("      IN      | Funcion de la ROM ");
$monitor("      %b               %b", I, O);
I = 7'b??????0;
#2 I = 7'b00001?1;
#2 I = 7'b00000?1;
#2 I = 7'b00011?1;
#2 I = 7'b00010?1;
#2 I = 7'b0010??1;
#2 I = 7'b0011??1;
#2 I = 7'b0100??1;
#2 I = 7'b0101??1;
#2 I = 7'b0110??1;
#2 I = 7'b0111??1;
#2 I = 7'b1000?11;
#2 I = 7'b1000?01;
#2 I = 7'b1001?11;
#2 I = 7'b1001?01;
#2 I = 7'b1010??1;
#2 I = 7'b1011??1;
#2 I = 7'b1100??1;
#2 I = 7'b1101??1;
#2 I = 7'b1110??1;
#2 I = 7'b1111??1;
#2 I = 7'b10110?1;
#2 I = 7'b00111?1;
#2 I = 7'b0110?01;
#2 I = 7'b01110?1;
#2 I = 7'b1010101;

end
initial
  #50 $finish;

initial begin
  $dumpfile("Ejercicio5_tb.vcd");
  $dumpvars(0, testbench);
end
endmodule

LAB09/Ejercicio5 lab9 /Ejercicio5_tb.vcd
$date
	Fri Oct 30 22:54:01 2020
$end
$version
	Icarus Verilog
$end
$timescale
	1ps
$end
$scope module testbench $end
$var wire 13 ! O [12:0] $end
$var reg 7 " I [6:0] $end
$scope module MROM $end
$var wire 7 # I [6:0] $end
$var reg 13 $ O [12:0] $end
$upscope $end
$upscope $end
$enddefinitions $end
#0
$dumpvars
bx $
bx #
bx "
bx !
$end
#1
b1000000001000 !
b1000000001000 $
bz0 "
bz0 #
#3
b100000001000 !
b100000001000 $
b1z1 "
b1z1 #
#5
b1000000001000 !
b1000000001000 $
b0z1 "
b0z1 #
#7
b11z1 "
b11z1 #
#9
b100000001000 !
b100000001000 $
b10z1 "
b10z1 #
#11
b1001000010 !
b1001000010 $
b10zz1 "
b10zz1 #
#13
b1001001100000 !
b1001001100000 $
b11zz1 "
b11zz1 #
#15
b11010000010 !
b11010000010 $
b100zz1 "
b100zz1 #
#17
b11010000100 !
b11010000100 $
b101zz1 "
b101zz1 #
#19
b1011010100000 !
b1011010100000 $
b110zz1 "
b110zz1 #
#21
b1000000111000 !
b1000000111000 $
b111zz1 "
b111zz1 #
#23
b100000001000 !
b100000001000 $
b1000z11 "
b1000z11 #
#25
b1000000001000 !
b1000000001000 $
b1000z01 "
b1000z01 #
#27
b1001z11 "
b1001z11 #
#29
b100000001000 !
b100000001000 $
b1001z01 "
b1001z01 #
#31
b11011000010 !
b11011000010 $
b1010zz1 "
b1010zz1 #
#33
b1011011100000 !
b1011011100000 $
b1011zz1 "
b1011zz1 #
#35
b100000001000 !
b100000001000 $
b1100zz1 "
b1100zz1 #
#37
b1001 !
b1001 $
b1101zz1 "
b1101zz1 #
#39
b11100000010 !
b11100000010 $
b1110zz1 "
b1110zz1 #
#41
b1011100100000 !
b1011100100000 $
b1111zz1 "
b1111zz1 #
#43
b1011011100000 !
b1011011100000 $
b10110z1 "
b10110z1 #
#45
b1001001100000 !
b1001001100000 $
b111z1 "
b111z1 #
#47
b1011010100000 !
b1011010100000 $
b110z01 "
b110z01 #
#49
b1000000111000 !
b1000000111000 $
b1110z1 "
b1110z1 #
