LAB09/Ejercicio1 lab9/Ejercicio1.v

//Flip FLop de 1 bit
module flipD1(input wire CLK, RESET, EN, D, output reg Q);
  always @ (posedge CLK or posedge RESET)begin
    if(RESET)
      Q <= 1'b0;
    else if (EN)
      Q <= D;
  end
endmodule


//Flip FLop de 2 bits
module flipD2(input wire CLK, RESET, EN, input wire [0:1]D2, output wire [0:1]Q2);

flipD1 F2_1(CLK, RESET, EN, D2[0], Q2[0]);
flipD1 F2_2(CLK, RESET, EN, D2[1], Q2[1]);
endmodule

//Flip FLop de 4 bits
module flipD4(input wire CLK, RESET, EN, input wire [0:3]D4, output wire [0:3]Q4);
flipD2 F4_1(CLK, RESET, EN, D4[0:1], Q4[0:1]);
flipD2 F4_2(CLK, RESET, EN, D4[2:3], Q4[2:3]);
endmodule

LAB09/Ejercicio1 lab9/Ejercicio1_tb.v
module testbench();

reg CLK, RESET, EN, D;
reg [0:1]D2;
reg [0:3]D4;

wire Q;
wire [0:1]Q2;
wire [0:3]Q4;

flipD1 F1(CLK, RESET, EN, D, Q);
flipD2 F2(CLK, RESET, EN, D2, Q2);
flipD4 F4(CLK, RESET, EN, D4, Q4);

initial begin
#1

$display("Clok|RESET|EN |  D |  D2  |   D4  |  Q   |   Q2   |  Q4  |");
$monitor(" %b     %b     %b   %b     %b      %b    %b      %b      %b ", CLK, RESET, EN, D, D2, D4, Q, Q2, Q4);
CLK = 0; RESET = 0; EN = 0; D = 0; D2 = 2'b00; D4 = 4'b0000;

#2 RESET = 1;
#2 RESET = 0;
#2 EN = 1;
#2 D = 1; D2 = 2'b01; D4 = 4'b0101;
#2 D2 = 2'b10; D4 = 4'b0011;
#2 D2 = 2'b01; D4 = 4'b0101;
#2 D = 0;
end
always
#1 CLK = ~CLK;

initial
#30 $finish;

initial begin
  $dumpfile("Ejercicio1_tb.vcd");
  $dumpvars(0, testbench);
end
endmodule

LAB09/Ejercicio1 lab9/Ejercicio1_tb.vcd
$date
	Fri Oct 30 12:10:03 2020
$end
$version
	Icarus Verilog
$end
$timescale
	1ps
$end
$scope module testbench $end
$var wire 4 ! Q4 [0:3] $end
$var wire 2 " Q2 [0:1] $end
$var wire 1 # Q $end
$var reg 1 $ CLK $end
$var reg 1 % D $end
$var reg 2 & D2 [0:1] $end
$var reg 4 ' D4 [0:3] $end
$var reg 1 ( EN $end
$var reg 1 ) RESET $end
$scope module F1 $end
$var wire 1 $ CLK $end
$var wire 1 % D $end
$var wire 1 ( EN $end
$var wire 1 ) RESET $end
$var reg 1 # Q $end
$upscope $end
$scope module F2 $end
$var wire 1 $ CLK $end
$var wire 2 * D2 [0:1] $end
$var wire 1 ( EN $end
$var wire 1 ) RESET $end
$var wire 2 + Q2 [0:1] $end
$scope module F2_1 $end
$var wire 1 $ CLK $end
$var wire 1 , D $end
$var wire 1 ( EN $end
$var wire 1 ) RESET $end
$var reg 1 - Q $end
$upscope $end
$scope module F2_2 $end
$var wire 1 $ CLK $end
$var wire 1 . D $end
$var wire 1 ( EN $end
$var wire 1 ) RESET $end
$var reg 1 / Q $end
$upscope $end
$upscope $end
$scope module F4 $end
$var wire 1 $ CLK $end
$var wire 4 0 D4 [0:3] $end
$var wire 1 ( EN $end
$var wire 1 ) RESET $end
$var wire 4 1 Q4 [0:3] $end
$scope module F4_1 $end
$var wire 1 $ CLK $end
$var wire 2 2 D2 [0:1] $end
$var wire 1 ( EN $end
$var wire 1 ) RESET $end
$var wire 2 3 Q2 [0:1] $end
$scope module F2_1 $end
$var wire 1 $ CLK $end
$var wire 1 4 D $end
$var wire 1 ( EN $end
$var wire 1 ) RESET $end
$var reg 1 5 Q $end
$upscope $end
$scope module F2_2 $end
$var wire 1 $ CLK $end
$var wire 1 6 D $end
$var wire 1 ( EN $end
$var wire 1 ) RESET $end
$var reg 1 7 Q $end
$upscope $end
$upscope $end
$scope module F4_2 $end
$var wire 1 $ CLK $end
$var wire 2 8 D2 [0:1] $end
$var wire 1 ( EN $end
$var wire 1 ) RESET $end
$var wire 2 9 Q2 [0:1] $end
$scope module F2_1 $end
$var wire 1 $ CLK $end
$var wire 1 : D $end
$var wire 1 ( EN $end
$var wire 1 ) RESET $end
$var reg 1 ; Q $end
$upscope $end
$scope module F2_2 $end
$var wire 1 $ CLK $end
$var wire 1 < D $end
$var wire 1 ( EN $end
$var wire 1 ) RESET $end
$var reg 1 = Q $end
$upscope $end
$upscope $end
$upscope $end
$upscope $end
$enddefinitions $end
#0
$dumpvars
x=
x<
x;
x:
bx 9
bx 8
x7
x6
x5
x4
bx 3
bx 2
bx 1
bx 0
x/
x.
x-
x,
bx +
bx *
x)
x(
bx '
bx &
x%
x$
x#
bx "
bx !
$end
#1
04
06
0:
0<
b0 2
b0 8
0,
0.
b0 '
b0 0
b0 &
b0 *
0%
0(
0)
1$
#2
0$
#3
0=
b0 9
0;
07
b0 !
b0 1
b0 3
05
0/
b0 "
b0 +
0-
0#
1$
1)
#4
0$
#5
1$
0)
#6
0$
#7
1$
1(
#8
0$
#9
1#
b1 "
b1 +
1/
16
1<
b1 2
b1 8
1.
1$
b101 '
b101 0
b1 &
b1 *
1%
#10
0$
#11
b1 9
1=
b101 !
b101 1
b1 3
17
0/
b10 "
b10 +
1-
06
1:
b0 2
b11 8
1,
0.
1$
b11 '
b11 0
b10 &
b10 *
#12
0$
#13
0-
b1 "
b1 +
1/
b0 3
07
b11 !
b11 1
b11 9
1;
16
0:
b1 2
b1 8
0,
1.
1$
b101 '
b101 0
b1 &
b1 *
#14
0$
#15
b1 9
0;
b101 !
b101 1
b1 3
17
0#
1$
0%
