Lab05/Lab5E1.v
module M2 (input wire J0, J1, m, output wire  Y);
  assign Y= m ? J1 : J0;
endmodule

module M4(input wire J0, J1, J2, J3, m0, m1, output wire Y1);

  wire s0, s1;

  M2 u0(J0, J1, m0, s0);
  M2 u1(J2, J3, m0, s1);
  M2 u2(s0, s1, m1, Y1);
endmodule

module M8 (input wire J0, J1, J2, J3, J4, J5, J6, J7, m0, m1, m2, output wire Y2 );
  wire s2, s3;

  M4 u3(J0, J1, J2, J3, m0, m1, s2);
  M4 u4(J4, J5, J6, J7, m0, m1, s3);
  M2 u5(s2, s3, m2, Y2);

endmodule

module T1M8(input wire A, B, C, output wire Y3);

  wire S, N;
  assign S = 1;
  assign N = 0;

  M8 T18(N, S, S, N, S, N, N, S, A, B, C, Y3);
endmodule


module T1M4(input wire A, B, C, output wire Y4);
  wire SC, NC;

  assign SC = C;
  assign NC = ~C;

  M4 T14(SC, NC, NC, SC, A, B, Y4);
endmodule


module T1M2(input wire A, B, C, output wire Y5);

  wire n0, n1;
  assign n0 = (B^C);
  assign n1 = ~(B^C);

  M2 T12(n0, n1, A, Y5);
endmodule

module T2M8(input wire A, B, C, output wire Y6);

  wire s, n;
  assign s = 1;
  assign n = 0;

  M8 T28(s, n, n, n, n, s, s, n, A, B, C, Y6);
endmodule

module T2M4(input wire A, B, C, output wire Y7);
  wire G, CS, CN;
  assign G = 0;
  assign CS = C;
  assign CN = ~C;

  M4 T24(CN, G, CS, CN, A, B, Y7);
endmodule

module T2M2(input wire A, B, C, output wire Y8);

  wire N0, N1;
  assign N0 = ~(B|C);
  assign N1 = (B^C);

  M2 T22(N0, N1, A, Y8);
endmodule

Lab05/Lab5E1_tb.v
module testbench();
  reg pb1, pb2, pb3, pb4, pb5, pb6, pb7, pb8, pb9, PB1, PB2, PB3, PB4, PB5, PB6, PB7, PB8, PB9;
  wire led1, led2, led3, LED1, LED2, LED3;
  T1M8 T18(pb1, pb2, pb3, led1);
  T1M4 T14(pb4, pb5, pb6, led2);
  T1M2 T12(pb7, pb8, pb9, led3);
  T2M8 T28(PB1, PB2, PB3, LED1);
  T2M4 T24(PB4, PB5, PB6, LED2);
  T2M2 T22(PB7, PB8, PB9, LED3);

  initial begin
  #1
    $display (" Mux 8:1 T1");
    $display("A B C | Y");
    $monitor("%b %b %b | %b", pb1, pb2, pb3, led1);
    pb1 = 0; pb2 = 0; pb3 = 0;
  #1 pb3 = 1;
  #1 pb2 = 1; pb3 = 0;
  #1 pb3 = 1;
  #1 pb1 = 1; pb2 = 0; pb3 = 0;
  #1 pb3 = 1;
  #1 pb2 = 1; pb3 = 0;
  #1 pb3 = 1;

  end

  initial begin
  #9
    $display (" Mux 4:1 T1");
    $display("A B C | Y");
    $monitor("%b %b %b | %b", pb4, pb5, pb6, led2);
    pb4 = 0; pb5 = 0; pb6 = 0;
  #1 pb6 = 1;
  #1 pb5 = 1; pb6 = 0;
  #1 pb6 = 1;
  #1 pb4 = 1; pb5 = 0; pb6 = 0;
  #1 pb6 = 1;
  #1 pb5 = 1; pb6 = 0;
  #1 pb6 = 1;

  end

  initial begin
  #19
    $display (" Mux 2:1 T1");
    $display("A B C | Y");
    $monitor("%b %b %b | %b", pb7, pb8, pb9, led3);
    pb7 = 0; pb8 = 0; pb9 = 0;
  #1 pb9 = 1;
  #1 pb8 = 1; pb9 = 0;
  #1 pb9 = 1;
  #1 pb7 = 1; pb8 = 0; pb9 = 0;
  #1 pb9 = 1;
  #1 pb8 = 1; pb9 = 0;
  #1 pb9 = 1;
  end

  initial begin
  #29
    $display (" Mux 8:1 T2");
    $display("A B C | Y");
    $monitor("%b %b %b | %b", PB1, PB2, PB3, LED1);
    PB1 = 0; PB2 = 0; PB3 = 0;
  #1 PB3 = 1;
  #1 PB2 = 1; PB3 = 0;
  #1 PB3 = 1;
  #1 PB1 = 1; PB2 = 0; PB3 = 0;
  #1 PB3 = 1;
  #1 PB2 = 1; PB3 = 0;
  #1 PB3 = 1;
  end
  initial begin
  #39
    $display (" Mux 4:1 T2");
    $display("A B C | Y");
    $monitor("%b %b %b | %b", PB4, PB5, PB6, LED2);
    PB4 = 0; PB5 = 0; PB6 = 0;
  #1 PB6 = 1;
  #1 PB5 = 1; PB6 = 0;
  #1 PB6 = 1;
  #1 PB4 = 1; PB5 = 0; PB6 = 0;
  #1 PB6 = 1;
  #1 PB5 = 1; PB6 = 0;
  #1 PB6 = 1;

  end
  initial begin
  #49
    $display (" Mux 2:1 T2");
    $display("A B C | Y");
    $monitor("%b %b %b | %b", PB7, PB8, PB9, LED3);
    PB7 = 0; PB8 = 0; PB9 = 0;
  #1 PB9 = 1;
  #1 PB8 = 1; PB9 = 0;
  #1 PB9 = 1;
  #1 PB7 = 1; PB8 = 0; PB9 = 0;
  #1 PB9 = 1;
  #1 PB8 = 1; PB9 = 0;
  #1 PB9 = 1;

  end

  initial
  #200 $finish;
  initial begin
    $dumpfile("Lab5E1_tb.vcd");
    $dumpvars(0, testbench);
  end
endmodule

Lab05/Lab5E1_tb.vcd
$date
	Sun Aug 16 10:36:27 2020
$end
$version
	Icarus Verilog
$end
$timescale
	1ps
$end
$scope module testbench $end
$var wire 1 ! led3 $end
$var wire 1 " led2 $end
$var wire 1 # led1 $end
$var wire 1 $ LED3 $end
$var wire 1 % LED2 $end
$var wire 1 & LED1 $end
$var reg 1 ' PB1 $end
$var reg 1 ( PB2 $end
$var reg 1 ) PB3 $end
$var reg 1 * PB4 $end
$var reg 1 + PB5 $end
$var reg 1 , PB6 $end
$var reg 1 - PB7 $end
$var reg 1 . PB8 $end
$var reg 1 / PB9 $end
$var reg 1 0 pb1 $end
$var reg 1 1 pb2 $end
$var reg 1 2 pb3 $end
$var reg 1 3 pb4 $end
$var reg 1 4 pb5 $end
$var reg 1 5 pb6 $end
$var reg 1 6 pb7 $end
$var reg 1 7 pb8 $end
$var reg 1 8 pb9 $end
$scope module T12 $end
$var wire 1 6 A $end
$var wire 1 7 B $end
$var wire 1 8 C $end
$var wire 1 9 n0 $end
$var wire 1 : n1 $end
$var wire 1 ! Y5 $end
$scope module T12 $end
$var wire 1 9 J0 $end
$var wire 1 : J1 $end
$var wire 1 6 m $end
$var wire 1 ! Y $end
$upscope $end
$upscope $end
$scope module T14 $end
$var wire 1 3 A $end
$var wire 1 4 B $end
$var wire 1 5 C $end
$var wire 1 ; NC $end
$var wire 1 < SC $end
$var wire 1 " Y4 $end
$scope module T14 $end
$var wire 1 < J0 $end
$var wire 1 ; J1 $end
$var wire 1 ; J2 $end
$var wire 1 < J3 $end
$var wire 1 3 m0 $end
$var wire 1 4 m1 $end
$var wire 1 = s1 $end
$var wire 1 > s0 $end
$var wire 1 " Y1 $end
$scope module u0 $end
$var wire 1 < J0 $end
$var wire 1 ; J1 $end
$var wire 1 3 m $end
$var wire 1 > Y $end
$upscope $end
$scope module u1 $end
$var wire 1 ; J0 $end
$var wire 1 < J1 $end
$var wire 1 3 m $end
$var wire 1 = Y $end
$upscope $end
$scope module u2 $end
$var wire 1 > J0 $end
$var wire 1 = J1 $end
$var wire 1 4 m $end
$var wire 1 " Y $end
$upscope $end
$upscope $end
$upscope $end
$scope module T18 $end
$var wire 1 0 A $end
$var wire 1 1 B $end
$var wire 1 2 C $end
$var wire 1 ? N $end
$var wire 1 @ S $end
$var wire 1 # Y3 $end
$scope module T18 $end
$var wire 1 ? J0 $end
$var wire 1 @ J1 $end
$var wire 1 @ J2 $end
$var wire 1 ? J3 $end
$var wire 1 @ J4 $end
$var wire 1 ? J5 $end
$var wire 1 ? J6 $end
$var wire 1 @ J7 $end
$var wire 1 0 m0 $end
$var wire 1 1 m1 $end
$var wire 1 2 m2 $end
$var wire 1 A s3 $end
$var wire 1 B s2 $end
$var wire 1 # Y2 $end
$scope module u3 $end
$var wire 1 ? J0 $end
$var wire 1 @ J1 $end
$var wire 1 @ J2 $end
$var wire 1 ? J3 $end
$var wire 1 0 m0 $end
$var wire 1 1 m1 $end
$var wire 1 C s1 $end
$var wire 1 D s0 $end
$var wire 1 B Y1 $end
$scope module u0 $end
$var wire 1 ? J0 $end
$var wire 1 @ J1 $end
$var wire 1 0 m $end
$var wire 1 D Y $end
$upscope $end
$scope module u1 $end
$var wire 1 @ J0 $end
$var wire 1 ? J1 $end
$var wire 1 0 m $end
$var wire 1 C Y $end
$upscope $end
$scope module u2 $end
$var wire 1 D J0 $end
$var wire 1 C J1 $end
$var wire 1 1 m $end
$var wire 1 B Y $end
$upscope $end
$upscope $end
$scope module u4 $end
$var wire 1 @ J0 $end
$var wire 1 ? J1 $end
$var wire 1 ? J2 $end
$var wire 1 @ J3 $end
$var wire 1 0 m0 $end
$var wire 1 1 m1 $end
$var wire 1 E s1 $end
$var wire 1 F s0 $end
$var wire 1 A Y1 $end
$scope module u0 $end
$var wire 1 @ J0 $end
$var wire 1 ? J1 $end
$var wire 1 0 m $end
$var wire 1 F Y $end
$upscope $end
$scope module u1 $end
$var wire 1 ? J0 $end
$var wire 1 @ J1 $end
$var wire 1 0 m $end
$var wire 1 E Y $end
$upscope $end
$scope module u2 $end
$var wire 1 F J0 $end
$var wire 1 E J1 $end
$var wire 1 1 m $end
$var wire 1 A Y $end
$upscope $end
$upscope $end
$scope module u5 $end
$var wire 1 B J0 $end
$var wire 1 A J1 $end
$var wire 1 2 m $end
$var wire 1 # Y $end
$upscope $end
$upscope $end
$upscope $end
$scope module T22 $end
$var wire 1 - A $end
$var wire 1 . B $end
$var wire 1 / C $end
$var wire 1 G N0 $end
$var wire 1 H N1 $end
$var wire 1 $ Y8 $end
$scope module T22 $end
$var wire 1 G J0 $end
$var wire 1 H J1 $end
$var wire 1 - m $end
$var wire 1 $ Y $end
$upscope $end
$upscope $end
$scope module T24 $end
$var wire 1 * A $end
$var wire 1 + B $end
$var wire 1 , C $end
$var wire 1 I CN $end
$var wire 1 J CS $end
$var wire 1 K G $end
$var wire 1 % Y7 $end
$scope module T24 $end
$var wire 1 I J0 $end
$var wire 1 K J1 $end
$var wire 1 J J2 $end
$var wire 1 I J3 $end
$var wire 1 * m0 $end
$var wire 1 + m1 $end
$var wire 1 L s1 $end
$var wire 1 M s0 $end
$var wire 1 % Y1 $end
$scope module u0 $end
$var wire 1 I J0 $end
$var wire 1 K J1 $end
$var wire 1 * m $end
$var wire 1 M Y $end
$upscope $end
$scope module u1 $end
$var wire 1 J J0 $end
$var wire 1 I J1 $end
$var wire 1 * m $end
$var wire 1 L Y $end
$upscope $end
$scope module u2 $end
$var wire 1 M J0 $end
$var wire 1 L J1 $end
$var wire 1 + m $end
$var wire 1 % Y $end
$upscope $end
$upscope $end
$upscope $end
$scope module T28 $end
$var wire 1 ' A $end
$var wire 1 ( B $end
$var wire 1 ) C $end
$var wire 1 N n $end
$var wire 1 O s $end
$var wire 1 & Y6 $end
$scope module T28 $end
$var wire 1 O J0 $end
$var wire 1 N J1 $end
$var wire 1 N J2 $end
$var wire 1 N J3 $end
$var wire 1 N J4 $end
$var wire 1 O J5 $end
$var wire 1 O J6 $end
$var wire 1 N J7 $end
$var wire 1 ' m0 $end
$var wire 1 ( m1 $end
$var wire 1 ) m2 $end
$var wire 1 P s3 $end
$var wire 1 Q s2 $end
$var wire 1 & Y2 $end
$scope module u3 $end
$var wire 1 O J0 $end
$var wire 1 N J1 $end
$var wire 1 N J2 $end
$var wire 1 N J3 $end
$var wire 1 ' m0 $end
$var wire 1 ( m1 $end
$var wire 1 R s1 $end
$var wire 1 S s0 $end
$var wire 1 Q Y1 $end
$scope module u0 $end
$var wire 1 O J0 $end
$var wire 1 N J1 $end
$var wire 1 ' m $end
$var wire 1 S Y $end
$upscope $end
$scope module u1 $end
$var wire 1 N J0 $end
$var wire 1 N J1 $end
$var wire 1 ' m $end
$var wire 1 R Y $end
$upscope $end
$scope module u2 $end
$var wire 1 S J0 $end
$var wire 1 R J1 $end
$var wire 1 ( m $end
$var wire 1 Q Y $end
$upscope $end
$upscope $end
$scope module u4 $end
$var wire 1 N J0 $end
$var wire 1 O J1 $end
$var wire 1 O J2 $end
$var wire 1 N J3 $end
$var wire 1 ' m0 $end
$var wire 1 ( m1 $end
$var wire 1 T s1 $end
$var wire 1 U s0 $end
$var wire 1 P Y1 $end
$scope module u0 $end
$var wire 1 N J0 $end
$var wire 1 O J1 $end
$var wire 1 ' m $end
$var wire 1 U Y $end
$upscope $end
$scope module u1 $end
$var wire 1 O J0 $end
$var wire 1 N J1 $end
$var wire 1 ' m $end
$var wire 1 T Y $end
$upscope $end
$scope module u2 $end
$var wire 1 U J0 $end
$var wire 1 T J1 $end
$var wire 1 ( m $end
$var wire 1 P Y $end
$upscope $end
$upscope $end
$scope module u5 $end
$var wire 1 Q J0 $end
$var wire 1 P J1 $end
$var wire 1 ) m $end
$var wire 1 & Y $end
$upscope $end
$upscope $end
$upscope $end
$upscope $end
$enddefinitions $end
#0
$dumpvars
xU
xT
xS
0R
xQ
xP
1O
0N
xM
xL
0K
xJ
xI
xH
xG
xF
xE
xD
xC
xB
xA
1@
0?
x>
x=
x<
x;
x:
x9
x8
x7
x6
x5
x4
x3
x2
x1
x0
x/
x.
x-
x,
x+
x*
x)
x(
x'
x&
x%
x$
x#
x"
x!
$end
#1
0#
0B
1A
0D
1C
1F
0E
02
01
00
#2
1#
12
#3
1B
0A
02
11
#4
0#
12
#5
1#
1D
0C
0F
1E
02
01
10
#6
0#
12
#7
0B
1A
02
11
#8
1#
12
#9
1=
1;
0"
0>
0<
05
04
03
#10
1"
0=
1>
0;
1<
15
#11
1=
0>
1;
1"
0<
05
14
#12
0"
0=
1>
0;
1<
15
#13
1"
1;
1>
0<
05
04
13
#14
0"
0>
1=
0;
1<
15
#15
1>
0=
1;
0"
0<
05
14
#16
1"
0>
1=
0;
1<
15
#19
0!
1:
09
08
07
06
#20
1!
0:
19
18
#21
08
17
#22
0!
1:
09
18
#23
1!
08
07
16
#24
0!
0:
19
18
#25
08
17
#26
1!
1:
09
18
#29
1&
1Q
0P
1S
0U
1T
0)
0(
0'
#30
0&
1)
#31
0Q
1P
0)
1(
#32
1&
1)
#33
0&
0S
1U
0T
0)
0(
1'
#34
1&
1)
#35
0&
0P
0)
1(
#36
1)
#39
1%
1M
1I
0L
0J
0,
0+
0*
#40
0%
0M
1L
0I
1J
1,
#41
1M
0L
1I
0%
0J
0,
1+
#42
1%
0M
1L
0I
1J
1,
#43
1I
0%
1L
0J
0,
0+
1*
#44
0L
0I
1J
1,
#45
1%
1L
1I
0J
0,
1+
#46
0%
0L
0I
1J
1,
#49
1$
1G
0H
0/
0.
0-
#50
0$
0G
1H
1/
#51
0/
1.
#52
0H
1/
#53
1G
0/
0.
1-
#54
0G
1$
1H
1/
#55
0/
1.
#56
0$
0H
1/
