LAB10/Ejercicio2 LAB10/Ejercicio2.v
// BUS Driver 1

module BT_4BL10_1 (input wire EN, input wire [0:3]I1, output wire [0:3]Y1);

assign Y1 = (EN) ? I1:4'bz;
endmodule

// BUS Driver 2
module BT_4BL10_2 (input wire EN, input wire [0:3]I2, output wire [0:3]Y2);

assign Y2 = (EN) ? I2:4'bz;
endmodule

// ALU
module ALUL10(input wire [3:0]A, input wire [3:0]B, input wire [2:0]COM, output reg C, Z, output reg [3:0]R, output reg [4:0]PM);


    always @ (A or B or COM)begin
// El case es como una pantalla de seleccion de comando
      case(COM)
      3'b000: begin
                  PM = 5'b00000;
                  PM = A;// deja pasar A
                  C = 1'b0;
                  Z = 1'b0;
                  R = PM[3:0];
              end

      3'b001: begin
                  PM = 5'b00000;
                  PM = A - B;// resta
                  R = PM[3:0];
                  C = PM[4];
                  Z = (PM == 5'b00000);
              end

      3'b011: begin
                  PM = 5'b00000;
                  PM = A + B;// resta
                  R = PM[3:0];
                  C = PM[4];
                  Z = (PM == 5'b00000);
              end

      3'b010: begin
                  PM = 5'b00000;
                  PM = B;// deja pasar B
                  C = 1'b0;
                  Z = 1'b0;
                  R = PM[3:0];
              end

      3'b100: begin
                  PM = 5'b00000;
                  PM = ~(A & B);// Nor
                  C = 1'b0;
                  Z = 1'b0;
                  R = PM[3:0];
              end
      endcase
    end
endmodule


// ACCU
module flipD1(input wire CLK, RESET, EN, D, output reg Q);
  always @ (posedge CLK or posedge RESET)begin
    if(RESET)
      Q <= 1'b0;
    else if (EN)
      Q <= D;
  end
endmodule

module flipD2(input wire CLK, RESET, EN, input wire [0:1]D2, output wire [0:1]Q2);

flipD1 F2_1(CLK, RESET, EN, D2[0], Q2[0]);
flipD1 F2_2(CLK, RESET, EN, D2[1], Q2[1]);
endmodule

module ACCU(input wire CLK, RESET, EN, input wire [0:3]D4, output wire [0:3]Q4);
flipD2 F4_1(CLK, RESET, EN, D4[0:1], Q4[0:1]);
flipD2 F4_2(CLK, RESET, EN, D4[2:3], Q4[2:3]);
endmodule



module CL10_2(input wire CLK, RESET, ENB1, ENB2, ENACU, input wire [0:3]BTI1, input wire [0:2]F, output wire [0:3]BTO2, output wire CC, ZC);
 wire [0:3]DB;
 wire [0:3]SALU;
 wire [0:3]SACCU;

 BT_4BL10_1 B1(ENB1, BTI1, DB);

 ALUL10 Alu(.A(SACCU), .B(DB), .COM(F), .C(CC), .Z(ZC), .R(SALU));

 ACCU acu(CLK, RESET, ENACU, SALU, SACCU);

 BT_4BL10_2 B2(ENB2, SALU, BTO2);

endmodule

LAB10/Ejercicio2 LAB10/Ejercicio2_tb.v
module testbench();

reg CLK, RESET, ENB1, ENB2, ENACU;
reg [0:3]BTI1;
reg [0:2]F;
wire [0:3]BTO2;
wire CC, ZC;

CL10_2 cl2(CLK, RESET, ENB1, ENB2, ENACU, BTI1, F, BTO2, CC, ZC);

initial begin 
#1
$display("Clk |  Reset|   Enable Buffer 1  | Enable Buffer 2  | Enable Accumulator  |  IN     |   Commands  |   Out   |   Carry  |   Zero  |");
$monitor(" %b     %b           %b                %b              %b                    %b           %b            %b        %b       %b ", CLK, RESET, ENB1, ENB2, ENACU, BTI1, F, BTO2, CC, ZC);
CLK = 0; RESET = 0; ENB1 = 0; ENB2 = 0; ENACU = 0; BTI1 = 4'b0000; F = 3'b000;

#1 RESET = 1;
#1 RESET = 0;
#1 ENB1 = 1; BTI1 = 4'b0001; F = 3'b010;
#1 ENB1 = 1; ENB2 = 1; ENACU = 1; BTI1 = 4'b1001; F = 3'b011;
#1 ENB1 = 1; ENB2 = 1; ENACU = 1; BTI1 = 4'b1101; F = 3'b001;
#1 ENB1 = 0; ENACU = 0;

end
always
#1 CLK = ~CLK;
initial
  #15 $finish;

initial begin
   $dumpfile("Ejercicio2_tb.vcd");
   $dumpvars(0, testbench);
end
endmodule

LAB10/Ejercicio2 LAB10/Ejercicio2_tb.vcd
$date
	Sat Nov  7 21:43:45 2020
$end
$version
	Icarus Verilog
$end
$timescale
	1ps
$end
$scope module testbench $end
$var wire 1 ! ZC $end
$var wire 1 " CC $end
$var wire 4 # BTO2 [0:3] $end
$var reg 4 $ BTI1 [0:3] $end
$var reg 1 % CLK $end
$var reg 1 & ENACU $end
$var reg 1 ' ENB1 $end
$var reg 1 ( ENB2 $end
$var reg 3 ) F [0:2] $end
$var reg 1 * RESET $end
$scope module cl2 $end
$var wire 4 + BTI1 [0:3] $end
$var wire 1 % CLK $end
$var wire 1 & ENACU $end
$var wire 1 ' ENB1 $end
$var wire 1 ( ENB2 $end
$var wire 3 , F [0:2] $end
$var wire 1 * RESET $end
$var wire 1 ! ZC $end
$var wire 4 - SALU [0:3] $end
$var wire 4 . SACCU [0:3] $end
$var wire 4 / DB [0:3] $end
$var wire 1 " CC $end
$var wire 4 0 BTO2 [0:3] $end
$scope module Alu $end
$var wire 3 1 COM [2:0] $end
$var wire 4 2 B [3:0] $end
$var wire 4 3 A [3:0] $end
$var reg 1 " C $end
$var reg 5 4 PM [4:0] $end
$var reg 4 5 R [3:0] $end
$var reg 1 ! Z $end
$upscope $end
$scope module B1 $end
$var wire 1 ' EN $end
$var wire 4 6 I1 [0:3] $end
$var wire 4 7 Y1 [0:3] $end
$upscope $end
$scope module B2 $end
$var wire 1 ( EN $end
$var wire 4 8 I2 [0:3] $end
$var wire 4 9 Y2 [0:3] $end
$upscope $end
$scope module acu $end
$var wire 1 % CLK $end
$var wire 4 : D4 [0:3] $end
$var wire 1 & EN $end
$var wire 1 * RESET $end
$var wire 4 ; Q4 [0:3] $end
$scope module F4_1 $end
$var wire 1 % CLK $end
$var wire 2 < D2 [0:1] $end
$var wire 1 & EN $end
$var wire 1 * RESET $end
$var wire 2 = Q2 [0:1] $end
$scope module F2_1 $end
$var wire 1 % CLK $end
$var wire 1 > D $end
$var wire 1 & EN $end
$var wire 1 * RESET $end
$var reg 1 ? Q $end
$upscope $end
$scope module F2_2 $end
$var wire 1 % CLK $end
$var wire 1 @ D $end
$var wire 1 & EN $end
$var wire 1 * RESET $end
$var reg 1 A Q $end
$upscope $end
$upscope $end
$scope module F4_2 $end
$var wire 1 % CLK $end
$var wire 2 B D2 [0:1] $end
$var wire 1 & EN $end
$var wire 1 * RESET $end
$var wire 2 C Q2 [0:1] $end
$scope module F2_1 $end
$var wire 1 % CLK $end
$var wire 1 D D $end
$var wire 1 & EN $end
$var wire 1 * RESET $end
$var reg 1 E Q $end
$upscope $end
$scope module F2_2 $end
$var wire 1 % CLK $end
$var wire 1 F D $end
$var wire 1 & EN $end
$var wire 1 * RESET $end
$var reg 1 G Q $end
$upscope $end
$upscope $end
$upscope $end
$upscope $end
$upscope $end
$enddefinitions $end
#0
$dumpvars
xG
xF
xE
xD
bx C
bx B
xA
x@
x?
x>
bx =
bx <
bx ;
bx :
bx 9
bx 8
bx 7
bx 6
bx 5
bx 4
bx 3
bx 2
bx 1
bx 0
bx /
bx .
bx -
bx ,
bx +
x*
bx )
x(
x'
x&
x%
bx $
bx #
x"
x!
$end
#1
0!
0"
b0xxxx 4
bz #
bz 0
bz 9
bz /
bz 2
bz 7
b0 )
b0 ,
b0 1
b0 $
b0 +
b0 6
0&
0(
0'
0*
1%
#2
0>
0@
0D
0F
b0 <
b0 B
b0 -
b0 5
b0 8
b0 :
b0 4
0G
b0 C
0E
0A
b0 .
b0 3
b0 ;
b0 =
0?
0%
1*
#3
1%
0*
#4
1F
b1 B
b1 -
b1 5
b1 8
b1 :
b1 4
b1 /
b1 2
b1 7
0%
b10 )
b10 ,
b10 1
b1 $
b1 +
b1 6
1'
#5
1D
0F
b10 B
b1 .
b1 3
b1 ;
b1 C
1G
1>
b10 <
b1010 -
b1010 5
b1010 8
b1010 :
b1010 4
b1001 /
b1001 2
b1001 7
b1010 #
b1010 0
b1010 9
1%
b11 )
b11 ,
b11 1
b1001 $
b1001 +
b1001 6
1&
1(
#6
0>
1@
0D
b100 #
b100 0
b100 9
b1 <
b0 B
1"
b100 -
b100 5
b100 8
b100 :
b10100 4
b1101 /
b1101 2
b1101 7
0%
b1 )
b1 ,
b1 1
b1101 $
b1101 +
b1101 6
#7
x>
x@
xD
xF
bx #
bx 0
bx 9
bx <
bx B
x!
x"
bx -
bx 5
bx 8
bx :
bx 4
bz /
bz 2
bz 7
1%
0&
0'
